{
  "locations": [
    {
      "name": "Березанський лиман",
      "coordinates": {
        "latitude": 46.832,
        "longitude": 31.518
      },
      "note": "Координати центральної частини лиману."
    },
    {
      "name": "Дніпровське водосховище",
      "coordinates": {
        "latitude": 47.95,
        "longitude": 35.15
      },
      "note": "Координати центральної частини водосховища, поблизу м. Запоріжжя."
    },
    {
      "name": "Дніпровсько-Бузька гирлова система",
      "coordinates": {
        "latitude": 46.61,
        "longitude": 31.97
      },
      "note": "Координати місця злиття Дніпровського та Бузького лиманів."
    },
    {
      "name": "Кам'янське водосховище",
      "coordinates": {
        "latitude": 48.75,
        "longitude": 34.33
      },
      "note": "Координати центральної частини водосховища."
    },
    {
      "name": "Канівське водосховище",
      "coordinates": {
        "latitude": 49.95,
        "longitude": 31.45
      },
      "note": "Координати центральної частини водосховища."
    },
    {
      "name": "Київське водосховище",
      "coordinates": {
        "latitude": 50.93,
        "longitude": 30.5
      },
      "note": "Координати центральної частини водосховища, на північ від Києва."
    },
    {
      "name": "Кременчуцьке водосховище",
      "coordinates": {
        "latitude": 49.37,
        "longitude": 32.75
      },
      "note": "Координати центральної частини найбільшого водосховища на Дніпрі."
    },
    {
      "name": "Тилігульський лиман",
      "coordinates": {
        "latitude": 46.85,
        "longitude": 31.15
      },
      "note": "Координати центральної частини лиману."
    },
    {
      "name": "пониззя річки Дністер та Дністровський лиман",
      "coordinates": {
        "latitude": 46.22,
        "longitude": 30.45
      },
      "note": "Координати центральної частини Дністровського лиману."
    },
    {
      "name": "річка Десна з озерами в межах Чернігівської області",
      "coordinates": {
        "latitude": 51.50,
        "longitude": 31.30
      },
      "note": "Приблизні координати річки Десна біля м. Чернігів."
    },
    {
      "name": "річка Дніпро в межах Чернігівської області",
      "coordinates": {
        "latitude": 51.25,
        "longitude": 30.65
      },
      "note": "Приблизні координати річки Дніпро на межі Київської та Чернігівської областей."
    },
    {
      "name": "річка Дунай",
      "coordinates": {
        "latitude": 45.40,
        "longitude": 29.59
      },
      "note": "Координати української частини дельти Дунаю, поблизу м. Вилкове."
    }
  ]
}